image_processing_abevilaqua/__init__.py
image_processing_abevilaqua/processing/__init__.py
image_processing_abevilaqua/processing/combination.py
image_processing_abevilaqua/processing/transformation.py
image_processing_abevilaqua/utils/__init__.py
image_processing_abevilaqua/utils/io.py
image_processing_abevilaqua/utils/plot.py
image_processing_abevilaqua-0.0.1.dist-info/METADATA
image_processing_abevilaqua-0.0.1.dist-info/WHEEL
image_processing_abevilaqua-0.0.1.dist-info/top_level.txt
image_processing_abevilaqua-0.0.1.dist-info/RECORD
