Metadata-Version: 2.1
Name: image-processing-abevilaqua
Version: 0.0.1
Summary: My short description
Home-page: https://github.com/andrembevilaqua/image_processing_abevilaqua
Author: Andre Bevilaqua
Author-email: andrebevilaqua@hotmail.com
License: UNKNOWN
Platform: UNKNOWN
Requires-Python: >=3.8
